{
  "pkg":[
    {
      "sku":"H-INDIE-TRIAL",
      "type":"PKG",
      "sub_type":"USER",
      "quota_required":"pkg.user",
      "display_name":"Indie",
      "pricing_model":"FREE",
      "subscription_type":"TRIAL",
      "time_unit":"DAY",
      "pricing_formula":"0.1",
      "display_price_usd":{
        "per_month_m2m":"3",
        "per_month_apm":"2.5"
      },
      "quota":{
        "pkg.user":10,
        "phabricator.disk_gb":20,
        "artifact.disk_gb":100,
        "ci.build_agent":-1,
        "cluster.kube_agent":-1,
        "db.paid.postgres":5,
        "db.paid.elasticsearch":5,
        "db.paid.influx":5
      },
      "date_started":"2016-01-01T00:00:00.000Z",
      "date_ended":"2030-01-01T00:00:00.000Z"
    },
    {
      "sku":"H-STARTUP-TRIAL",
      "type":"PKG",
      "sub_type":"USER",
      "quota_required":"pkg.user",
      "display_name":"Startup",
      "pricing_model":"FREE",
      "subscription_type":"TRIAL",
      "time_unit":"DAY",
      "pricing_formula":"0.1",
      "display_price_usd":{
        "per_month_m2m":"3",
        "per_month_apm":"2.5"
      },
      "quota":{
        "pkg.user":10,
        "phabricator.disk_gb":20,
        "artifact.disk_gb":100,
        "ci.build_agent":-1,
        "cluster.kube_agent":-1,
        "db.paid.postgres":5,
        "db.paid.elasticsearch":5,
        "db.paid.influx":5
      },
      "date_started":"2016-01-01T00:00:00.000Z",
      "date_ended":"2030-01-01T00:00:00.000Z"
    },
    {
      "sku":"H-PRO-TRIAL",
      "type":"PKG",
      "sub_type":"USER",
      "quota_required":"pkg.user",
      "display_name":"Professional",
      "pricing_model":"FREE",
      "subscription_type":"TRIAL",
      "time_unit":"DAY",
      "pricing_formula":"0.1",
      "display_price_usd":{
        "per_month_m2m":"3",
        "per_month_apm":"2.5"
      },
      "quota":{
        "pkg.user":10,
        "phabricator.disk_gb":20,
        "artifact.disk_gb":100,
        "ci.build_agent":-1,
        "cluster.kube_agent":-1,
        "db.paid.postgres":5,
        "db.paid.elasticsearch":5,
        "db.paid.influx":5
      },
      "date_started":"2016-01-01T00:00:00.000Z",
      "date_ended":"2030-01-01T00:00:00.000Z"
    },
    {
      "sku":"H-ENT-BETA",
      "type":"PKG",
      "sub_type":"USER",
      "quota_required":"pkg.user",
      "display_name":"Enterprise",
      "pricing_model":"FREE",
      "subscription_type":"BETA",
      "time_unit":"DAY",
      "pricing_formula":"0.1",
      "display_price_usd":{
        "per_month_m2m":"3",
        "per_month_apm":"2.5"
      },
      "quota":{
        "pkg.user":10,
        "phabricator.disk_gb":20,
        "artifact.disk_gb":100,
        "ci.build_agent":-1,
        "cluster.kube_agent":-1,
        "db.paid.postgres":5,
        "db.paid.elasticsearch":5,
        "db.paid.influx":5
      },
      "date_started":"2016-01-01T00:00:00.000Z",
      "date_ended":"2030-01-01T00:00:00.000Z"
    },
    {
      "sku":"P-BETA",
      "type":"PKG",
      "sub_type":"USER",
      "quota_required":"pkg.user",
      "display_name":"Private Installation",
      "pricing_model":"FREE",
      "subscription_type":"BETA",
      "time_unit":"DAY",
      "pricing_formula":"0.1",
      "display_price_usd":{
        "per_month_m2m":"3",
        "per_month_apm":"2.5"
      },
      "quota":{
        "pkg.user":10,
        "phabricator.disk_gb":20,
        "artifact.disk_gb":100,
        "ci.build_agent":-1,
        "cluster.kube_agent":-1,
        "db.paid.postgres":5,
        "db.paid.elasticsearch":5,
        "db.paid.influx":5
      },
      "date_started":"2016-01-01T00:00:00.000Z",
      "date_ended":"2030-01-01T00:00:00.000Z"
    },
    {
      "sku":"H-FREE",
      "type":"PKG",
      "sub_type":"USER",
      "quota_required":"pkg.user",
      "display_name":"Free",
      "pricing_model":"FREE",
      "subscription_type":"PRIMARY",
      "time_unit":"DAY",
      "pricing_formula":"0.1",
      "display_price_usd":{
        "per_month_m2m":"3",
        "per_month_apm":"2.5"
      },
      "quota":{
        "pkg.user":10,
        "phabricator.disk_gb":20,
        "artifact.disk_gb":100,
        "ci.build_agent":-1,
        "cluster.kube_agent":-1,
        "db.paid.postgres":5,
        "db.paid.elasticsearch":5,
        "db.paid.influx":5
      },
      "date_started":"2016-01-01T00:00:00.000Z",
      "date_ended":"2030-01-01T00:00:00.000Z"
    },
    {
      "sku":"H-M2M-INDIE",
      "type":"PKG",
      "sub_type":"USER",
      "quota_required":"pkg.user",
      "display_name":"Indie",
      "pricing_model":"M2M",
      "subscription_type":"PRIMARY",
      "time_unit":"DAY",
      "pricing_formula":"0.1",
      "display_price_usd":{
        "per_month_m2m":"3",
        "per_month_apm":"2.5"
      },
      "quota":{
        "pkg.user":10,
        "phabricator.disk_gb":20,
        "artifact.disk_gb":100,
        "ci.build_agent":-1,
        "cluster.kube_agent":-1,
        "db.paid.postgres":5,
        "db.paid.elasticsearch":5,
        "db.paid.influx":5
      },
      "date_started":"2016-01-01T00:00:00.000Z",
      "date_ended":"2030-01-01T00:00:00.000Z"
    },
    {
      "sku":"H-M2M-STARTUP",
      "type":"PKG",
      "sub_type":"USER",
      "quota_required":"pkg.user",
      "display_name":"Startup",
      "pricing_model":"M2M",
      "subscription_type":"PRIMARY",
      "time_unit":"DAY",
      "pricing_formula":"0.1",
      "display_price_usd":{
        "per_month_m2m":"3",
        "per_month_apm":"2.5"
      },
      "quota":{
        "pkg.user":10,
        "phabricator.disk_gb":20,
        "artifact.disk_gb":100,
        "ci.build_agent":-1,
        "cluster.kube_agent":-1,
        "db.paid.postgres":5,
        "db.paid.elasticsearch":5,
        "db.paid.influx":5
      },
      "date_started":"2016-01-01T00:00:00.000Z",
      "date_ended":"2030-01-01T00:00:00.000Z"
    },
    {
      "sku":"H-M2M-PRO",
      "type":"PKG",
      "sub_type":"USER",
      "quota_required":"pkg.user",
      "display_name":"Professional",
      "pricing_model":"M2M",
      "subscription_type":"PRIMARY",
      "time_unit":"DAY",
      "pricing_formula":"0.1",
      "display_price_usd":{
        "per_month_m2m":"3",
        "per_month_apm":"2.5"
      },
      "quota":{
        "pkg.user":10,
        "phabricator.disk_gb":20,
        "artifact.disk_gb":100,
        "ci.build_agent":-1,
        "cluster.kube_agent":-1,
        "db.paid.postgres":5,
        "db.paid.elasticsearch":5,
        "db.paid.influx":5
      },
      "date_started":"2016-01-01T00:00:00.000Z",
      "date_ended":"2030-01-01T00:00:00.000Z"
    },
    {
      "sku":"H-APM-INDIE",
      "type":"PKG",
      "sub_type":"USER",
      "quota_required":"pkg.user",
      "display_name":"Indie",
      "pricing_model":"APM",
      "subscription_type":"PRIMARY",
      "time_unit":"DAY",
      "pricing_formula":"0.1",
      "display_price_usd":{
        "per_month_m2m":"3",
        "per_month_apm":"2.5"
      },
      "quota":{
        "pkg.user":10,
        "phabricator.disk_gb":20,
        "artifact.disk_gb":100,
        "ci.build_agent":-1,
        "cluster.kube_agent":-1,
        "db.paid.postgres":5,
        "db.paid.elasticsearch":5,
        "db.paid.influx":5
      },
      "date_started":"2016-01-01T00:00:00.000Z",
      "date_ended":"2030-01-01T00:00:00.000Z"
    },
    {
      "sku":"H-APM-STARTUP",
      "type":"PKG",
      "sub_type":"USER",
      "quota_required":"pkg.user",
      "display_name":"Startup",
      "pricing_model":"APM",
      "subscription_type":"PRIMARY",
      "time_unit":"DAY",
      "pricing_formula":"0.1",
      "display_price_usd":{
        "per_month_m2m":"3",
        "per_month_apm":"2.5"
      },
      "quota":{
        "pkg.user":10,
        "phabricator.disk_gb":20,
        "artifact.disk_gb":100,
        "ci.build_agent":-1,
        "cluster.kube_agent":-1,
        "db.paid.postgres":5,
        "db.paid.elasticsearch":5,
        "db.paid.influx":5
      },
      "date_started":"2016-01-01T00:00:00.000Z",
      "date_ended":"2030-01-01T00:00:00.000Z"
    },
    {
      "sku":"H-APM-PRO",
      "type":"PKG",
      "sub_type":"USER",
      "quota_required":"pkg.user",
      "display_name":"Professional",
      "pricing_model":"APM",
      "subscription_type":"PRIMARY",
      "time_unit":"DAY",
      "pricing_formula":"0.1",
      "display_price_usd":{
        "per_month_m2m":"3",
        "per_month_apm":"2.5"
      },
      "quota":{
        "pkg.user":10,
        "phabricator.disk_gb":20,
        "artifact.disk_gb":100,
        "ci.build_agent":-1,
        "cluster.kube_agent":-1,
        "db.paid.postgres":5,
        "db.paid.elasticsearch":5,
        "db.paid.influx":5
      },
      "date_started":"2016-01-01T00:00:00.000Z",
      "date_ended":"2030-01-01T00:00:00.000Z"
    }
  ]
}
