{
  "definitions":{
    "pvPVDescribeRequest":{
      "properties":{
        "cluster":{
          "type":"string"
        },
        "name":{
          "type":"string"
        }
      },
      "type":"object"
    },
    "pvPVRegisterRequest":{
      "properties":{
        "cluster":{
          "type":"string"
        },
        "endpoint":{
          "type":"string"
        },
        "identifier":{
          "type":"string"
        },
        "name":{
          "type":"string"
        },
        "plugin":{
          "type":"string"
        },
        "size":{
          "type":"integer"
        }
      },
      "type":"object"
    },
    "pvPVUnregisterRequest":{
      "properties":{
        "cluster":{
          "type":"string"
        },
        "name":{
          "type":"string"
        }
      },
      "type":"object"
    }
  }
}